quantumsolve/__init__.py
quantumsolve/algorithm.py
quantumsolve/cs_eq.py
quantumsolve/math_eq.py
quantumsolve/physics_eq.py
quantumsolve/stat_eq.py
quantumsolve-0.0.5.dist-info/licenses/LICENSE.txt
quantumsolve-0.0.5.dist-info/METADATA
quantumsolve-0.0.5.dist-info/WHEEL
quantumsolve-0.0.5.dist-info/top_level.txt
quantumsolve-0.0.5.dist-info/RECORD
