Metadata-Version: 2.4
Name: quantumsolve
Version: 0.0.5
Summary: Famous math, physics, stats, and CS equations as Python functions.
Home-page: 
Author: Md Muzahidul Islam
Author-email: muzahidsife@gmail.com
License: MIT
Keywords: calculator equations math physics statistics computer science
Classifier: Development Status :: 5 - Production/Stable
Classifier: Intended Audience :: Education
Classifier: Operating System :: Microsoft :: Windows :: Windows 10
Classifier: License :: OSI Approved :: MIT License
Classifier: Programming Language :: Python :: 3
License-File: LICENSE.txt
Dynamic: author
Dynamic: author-email
Dynamic: classifier
Dynamic: description
Dynamic: description-content-type
Dynamic: keywords
Dynamic: license
Dynamic: license-file
Dynamic: summary
